cloudx_proxy/_1password.py
cloudx_proxy/__init__.py
cloudx_proxy/_version.py
cloudx_proxy/cli.py
cloudx_proxy/colors.py
cloudx_proxy/core.py
cloudx_proxy/setup.py
cloudx_proxy-0.16.0.dist-info/licenses/LICENSE
cloudx_proxy-0.16.0.dist-info/licenses/NOTICE
cloudx_proxy-0.16.0.dist-info/METADATA
cloudx_proxy-0.16.0.dist-info/WHEEL
cloudx_proxy-0.16.0.dist-info/entry_points.txt
cloudx_proxy-0.16.0.dist-info/top_level.txt
cloudx_proxy-0.16.0.dist-info/RECORD
