Metadata-Version: 2.4
Name: cloudx-proxy
Version: 0.16.0
Summary: SSH proxy command to connect VSCode with cloudX instance using AWS Systems Manager
Author-email: easytocloud <info@easytocloud.com>
License: MIT License
Project-URL: Homepage, https://github.com/easytocloud/cloudX-proxy
Project-URL: Repository, https://github.com/easytocloud/cloudX-proxy
Project-URL: Issues, https://github.com/easytocloud/cloudX-proxy/issues
Project-URL: Changelog, https://github.com/easytocloud/cloudX-proxy/blob/main/CHANGELOG.md
Keywords: aws,vscode,cloud9,cloudX,ssm,ssh,proxy
Classifier: Development Status :: 5 - Production/Stable
Classifier: Environment :: Console
Classifier: Intended Audience :: Developers
Classifier: License :: OSI Approved :: MIT License
Classifier: Operating System :: OS Independent
Classifier: Programming Language :: Python :: 3
Classifier: Programming Language :: Python :: 3.10
Classifier: Programming Language :: Python :: 3.11
Classifier: Programming Language :: Python :: 3.12
Classifier: Programming Language :: Python :: 3.13
Classifier: Topic :: Software Development :: Build Tools
Classifier: Topic :: System :: Systems Administration
Requires-Python: >=3.10
License-File: LICENSE
License-File: NOTICE
Requires-Dist: boto3>=1.34.0
Requires-Dist: click>=8.1.0
Dynamic: license-file
